{
  "commit": "53407797404f05612b774e233bec52951986013b",
  "repo_url": "https://github.com/os4ed/opensis-classic",
  "date": "2023-12-23T17:23:16",
  "languages": {
    "PHP": 10743698,
    "JavaScript": 5137228,
    "Less": 1062396,
    "CSS": 954637,
    "HTML": 834458,
    "ColdFusion": 119152,
    "SCSS": 72669,
    "Python": 38346,
    "Classic ASP": 35695,
    "Perl": 34857,
    "Lasso": 19627,
    "XSLT": 9680,
    "ASP.NET": 7429,
    "Raku": 1472,
    "Shell": 666
  },
  "size": 19072010
}
