{
  "commit": "b979c788a9b79b615457e94b6e9f709513fe2e27",
  "repo_url": "https://github.com/postgres/postgres",
  "date": "2021-08-09T20:56:33",
  "languages": {
    "C": 33169390,
    "PLpgSQL": 1712263,
    "Perl": 606004,
    "Yacc": 553615,
    "Makefile": 306848,
    "Lex": 202332,
    "Ruby": 136815,
    "Shell": 93080,
    "M4": 84819,
    "Roff": 32437,
    "Python": 18288,
    "Batchfile": 7886,
    "XS": 6983,
    "Emacs Lisp": 3488,
    "DTrace": 3480,
    "Assembly": 3265,
    "sed": 1231,
    "Raku": 698,
    "Csound Score": 157
  },
  "size": 36943079
}
