{
  "commit": "ae81bf668bf4781c0cb0bfe7709e2e2f3c57f2ed",
  "repo_url": "https://github.com/apache/orc",
  "date": "2018-02-06T21:55:02",
  "languages": {
    "C++": 15703784,
    "HTML": 14184844,
    "Java": 3229742,
    "Shell": 1693322,
    "C": 1471724,
    "Python": 1198017,
    "Makefile": 718665,
    "Assembly": 138199,
    "Ada": 89080,
    "M4": 78828,
    "CMake": 78747,
    "Pascal": 70297,
    "C#": 54012,
    "CSS": 51368,
    "SCSS": 36627,
    "DIGITAL Command Language": 27303,
    "Dockerfile": 8591,
    "Emacs Lisp": 7798,
    "Roff": 7559,
    "CLIPS": 5291,
    "Batchfile": 4273,
    "Perl": 3895,
    "Vim Script": 3731,
    "JavaScript": 3308,
    "SAS": 1847,
    "Module Management System": 1545,
    "Ruby": 60
  },
  "size": 38872457
}
