{
  "commit": "d7e5f7903de06e504aac4a3822a41d69e159e370",
  "repo_url": "https://github.com/isc-projects/bind9",
  "date": "2024-07-31T15:11:33",
  "languages": {
    "C": 12037620,
    "Shell": 2563178,
    "Python": 498015,
    "Perl": 231499,
    "M4": 120134,
    "Makefile": 54284,
    "XSLT": 39276,
    "SWIG": 5929,
    "XS": 4924,
    "Roff": 4483,
    "Emacs Lisp": 3926,
    "C++": 2900,
    "DTrace": 2621,
    "Jinja": 531,
    "SmPL": 473,
    "GDB": 25,
    "DIGITAL Command Language": 12
  },
  "size": 15569830
}
