{
  "commit": "502f4fe48a81a392756e173e39a861f8c8efe056",
  "repo_url": "https://github.com/super-linter/super-linter",
  "date": "2025-11-28T16:54:53",
  "languages": {
    "Shell": 367130,
    "Makefile": 23722,
    "Dockerfile": 21878,
    "Ruby": 20032,
    "JavaScript": 19872,
    "TeX": 16258,
    "Python": 7632,
    "CoffeeScript": 6964,
    "Jupyter Notebook": 6475,
    "HCL": 5298,
    "Perl": 4113,
    "C#": 3554,
    "PHP": 2909,
    "R": 2549,
    "Clojure": 2529,
    "Rust": 2514,
    "HTML": 2307,
    "PowerShell": 2167,
    "Java": 1926,
    "CSS": 1782,
    "Vue": 1154,
    "C++": 1131,
    "Go": 1118,
    "TypeScript": 1027,
    "Scala": 962,
    "Groovy": 961,
    "Lua": 511,
    "Kotlin": 264,
    "Gherkin": 204,
    "Dart": 173
  },
  "size": 529116
}
